goecharger/__init__.py
goecharger/goecharger.py
goecharger-0.1.0.dist-info/LICENSE
goecharger-0.1.0.dist-info/METADATA
goecharger-0.1.0.dist-info/WHEEL
goecharger-0.1.0.dist-info/top_level.txt
goecharger-0.1.0.dist-info/RECORD
