Metadata-Version: 2.1
Name: goecharger
Version: 0.1.0
Summary: A Python API for accessing the go-eCharger EV-Charger
Home-page: https://github.com/cathiele/goecharger
Author: Carsten Thiele
Author-email: software@carsten-thiele.de
License: UNKNOWN
Platform: UNKNOWN
Classifier: Programming Language :: Python :: 3
Classifier: License :: OSI Approved :: MIT License
Classifier: Operating System :: OS Independent
Provides: goecharger
Requires-Python: >=3.6
Requires-Dist: requests
